README
setup.py
oauth/__init__.py
oauth/client.py
oauth/consumer.py
oauth/data.py
oauth/exceptions.py
oauth/request.py
oauth/signature.py
oauth/token.py
oauth/utils.py
oauther.egg-info/PKG-INFO
oauther.egg-info/SOURCES.txt
oauther.egg-info/dependency_links.txt
oauther.egg-info/requires.txt
oauther.egg-info/top_level.txt