Metadata-Version: 1.0
Name: oauther
Version: 0.1
Summary: An simple oauth base client.
Home-page: http://github.com/carlitux/Python-OAuth-Client
Author: Luis C. Cruz
Author-email: carlitos.kyo@gmail.com
License: MIT License
Keywords: oauth client
Platform: UNKNOWN
Classifier: Development Status :: 4 - Beta
Classifier: Intended Audience :: Developers
Classifier: License :: OSI Approved :: MIT License
Classifier: Topic :: Software Development :: Libraries :: Python Modules
Classifier: Topic :: Internet
